adb_mcp/cli.py
adb_mcp-0.9.2.dist-info/METADATA
adb_mcp-0.9.2.dist-info/WHEEL
adb_mcp-0.9.2.dist-info/entry_points.txt
adb_mcp-0.9.2.dist-info/top_level.txt
adb_mcp-0.9.2.dist-info/RECORD
