Metadata-Version: 2.4
Name: adb-mcp
Version: 0.9.2
Summary: adb command tools with mcp
Requires-Python: >=3.12
Requires-Dist: mcp>=1.6.0
